[
        {
            "country": "United States",
            "name": "Vice East",
            "tvgid": "ViceEast.us"
        },
        {
            "country": "United States",
            "name": "Vice TV France",
            "tvgid": "ViceTVFrance.us"
        },
        {
            "country": "United States",
            "name": "Vida Mejor TV (KURK-LD4) Santa Rosa, CA",
            "tvgid": "KURKLD4.us"
        },
        {
            "country": "United States",
            "name": "Vida Vision (KLHO-DT3) Oklahoma City, OK",
            "tvgid": "KLHOLD3.us"
        },
        {
            "country": "United States",
            "name": "Vida Vision (KVHD-LD7) Los Angeles, CA",
            "tvgid": "KVHDLD7.us"
        },
        {
            "country": "United States",
            "name": "Vida Vision (KWDA-LD2) Dallas, TX",
            "tvgid": "KWDALD2.us"
        },
        {
            "country": "United States",
            "name": "Vida Vision (KZHO-LD2) Houston, TX",
            "tvgid": "KZHOLD2.us"
        },
        {
            "country": "United States",
            "name": "Vida Vision (WACX5) Orlando, FL",
            "tvgid": "WACX5.us"
        },
        {
            "country": "United States",
            "name": "Vien Thao TV",
            "tvgid": "VienThaoTV.us"
        },
        {
            "country": "United States",
            "name": "ViendoMovies",
            "tvgid": "ViendoMovies.us"
        },
        {
            "country": "United States",
            "name": "Viet Today TV (KTSF-DT5) San Francisco, CA",
            "tvgid": "KTSF5.us"
        },
        {
            "country": "United States",
            "name": "Vietface TV",
            "tvgid": "VietfaceTV.us"
        },
        {
            "country": "United States",
            "name": "VIETOP (WKTB-CD7) Norcross, GA",
            "tvgid": "WKTBCD7.us"
        },
        {
            "country": "United States",
            "name": "Vietv Network",
            "tvgid": "VietvNetwork.us"
        },
        {
            "country": "United States",
            "name": "Vivid Red",
            "tvgid": "VividRed.us"
        },
        {
            "country": "United States",
            "name": "Vivid Touch",
            "tvgid": "VividTouch.us"
        },
        {
            "country": "United States",
            "name": "Vivid TV",
            "tvgid": "VividTV.us"
        },
        {
            "country": "United States",
            "name": "Vivid TV Europe",
            "tvgid": "VividTVEurope.us"
        },
        {
            "country": "United States",
            "name": "Vivid TV Monthly Offer",
            "tvgid": "VividTVMonthlyOffer.us"
        },
        {
            "country": "United States",
            "name": "Vixen",
            "tvgid": "Vixen.us"
        },
        {
            "country": "United States",
            "name": "Vme Kids",
            "tvgid": "VmeKids.us"
        },
        {
            "country": "United States",
            "name": "Voz y Visión (K27OJ-D) El Paso, TX",
            "tvgid": "K27OJD.us"
        },
        {
            "country": "United States",
            "name": "VPOD-TV (WAOE-DT3) Peoria, IL",
            "tvgid": "WAOE3.us"
        },
        {
            "country": "United States",
            "name": "VTN (KVTH) Hot Springs, AR",
            "tvgid": "KVTHDT.us"
        },
        {
            "country": "United States",
            "name": "VTN (KVTJ) Jonesboro, AR",
            "tvgid": "KVTJDT.us"
        },
        {
            "country": "United States",
            "name": "VTN (KVTN) Little Rock, AR",
            "tvgid": "KVTNDT.us"
        },
        {
            "country": "United States",
            "name": "W24CS Reading, PA",
            "tvgid": "W24CSD.us"
        },
        {
            "country": "United States",
            "name": "W36DO-D3 Darby, PA",
            "tvgid": "W36DOD3.us"
        },
        {
            "country": "United States",
            "name": "WACX Altamonte Springs, FL",
            "tvgid": "WACX.us"
        },
        {
            "country": "United States",
            "name": "WADL - TV, Detroit, MI",
            "tvgid": "WADL.us"
        },
        {
            "country": "United States",
            "name": "WAGV- Harlan, KY",
            "tvgid": "WAGV.us"
        },
        {
            "country": "United States",
            "name": "WAPA (WAPA-TV) San Juan, PR",
            "tvgid": "WAPATV.us"
        },
        {
            "country": "United States",
            "name": "WAPA Deportes (WAPA-DT2) San Juan, PR",
            "tvgid": "WAPADT2.us"
        },
        {
            "country": "United States",
            "name": "Warner Channel Atlántico Sur",
            "tvgid": "WarnerChannelAtlanticoSur.us"
        },
        {
            "country": "United States",
            "name": "Warner Channel Brasil",
            "tvgid": "WarnerChannelBrasil.us"
        },
        {
            "country": "United States",
            "name": "Warner Channel México",
            "tvgid": "WarnerChannelMexico.us"
        },
        {
            "country": "United States",
            "name": "Warner Channel Panregional",
            "tvgid": "WarnerChannelPanregional.us"
        },
        {
            "country": "United States",
            "name": "Warner TV France",
            "tvgid": "WarnerTVFrance.us"
        },
        {
            "country": "United States",
            "name": "Warner TV Southeast Asia",
            "tvgid": "WarnerTVSoutheastAsia.us"
        },
        {
            "country": "United States",
            "name": "WARP-CD Tampa, FL",
            "tvgid": "WARPCD.us"
        },
        {
            "country": "United States",
            "name": "WARP-CD2 Tampa, FL",
            "tvgid": "WARPCD2.us"
        },
        {
            "country": "United States",
            "name": "WARP-CD3 Tampa, FL",
            "tvgid": "WARPCD3.us"
        },
        {
            "country": "United States",
            "name": "WARP-CD4 Tampa, FL",
            "tvgid": "WARPCD4.us"
        },
        {
            "country": "United States",
            "name": "WAXN Charlotte, NC",
            "tvgid": "WAXNTV.us"
        },
        {
            "country": "United States",
            "name": "WBEC-TV Boca Raton, FL",
            "tvgid": "WBECTV.us"
        },
        {
            "country": "United States",
            "name": "WBGU-DT2 Kids/Encore Bowling Green, OH",
            "tvgid": "WBGUTV2.us"
        },
        {
            "country": "United States",
            "name": "WBNA Louisville, KY",
            "tvgid": "WBNA.us"
        },
        {
            "country": "United States",
            "name": "WBNX Cleveland, OH",
            "tvgid": "WBNXTV.us"
        },
        {
            "country": "United States",
            "name": "WBPH Philadelphia, PA",
            "tvgid": "WBPHTV.us"
        },
        {
            "country": "United States",
            "name": "WBPH Philadelphia, PA (WSCG-LD8) Beaufort, SC",
            "tvgid": "WSCGLD8.us"
        },
        {
            "country": "United States",
            "name": "WBPH-D1 (WHDC-LD8) Charleston, SC",
            "tvgid": "WHDCLD8.us"
        },
        {
            "country": "United States",
            "name": "WBPH-DT2 Bethlehem, PA",
            "tvgid": "WBPHTV2.us"
        },
        {
            "country": "United States",
            "name": "WBPI (WHDC-LD3) Charleston, SC",
            "tvgid": "WHDCLD3.us"
        },
        {
            "country": "United States",
            "name": "WBPX-TV3 Hudson, NH",
            "tvgid": "WBPXTV3.us"
        },
        {
            "country": "United States",
            "name": "WDAY-TV3 (KBMY-DT3) Xtra Fargo, ND",
            "tvgid": "KBMYTV3.us"
        },
        {
            "country": "United States",
            "name": "WDAY-TV3 Xtra Fargo, ND",
            "tvgid": "WDAYTV3.us"
        },
        {
            "country": "United States",
            "name": "WDAZ-TV3 Xtra Fargo, ND",
            "tvgid": "WDAZTV3.us"
        },
        {
            "country": "United States",
            "name": "WDPX-TV2 Vineyard Haven, MA",
            "tvgid": "WDPXTV2.us"
        },
        {
            "country": "United States",
            "name": "WDPX-TV3 Vineyard Haven, MA",
            "tvgid": "WDPXTV3.us"
        },
        {
            "country": "United States",
            "name": "WDPX-TV4 Vineyard Haven, MA",
            "tvgid": "WDPXTV4.us"
        },
        {
            "country": "United States",
            "name": "WDPX-TV5 Vineyard Haven, MA",
            "tvgid": "WDPXTV5.us"
        },
        {
            "country": "United States",
            "name": "WDPX-TV6 Vineyard Haven, MA",
            "tvgid": "WDPXTV6.us"
        },
        {
            "country": "United States",
            "name": "We TV East",
            "tvgid": "WeTVEast.us"
        },
        {
            "country": "United States",
            "name": "We TV West",
            "tvgid": "WeTVWest.us"
        },
        {
            "country": "United States",
            "name": "Weather (KPSN-LD2) Payson, AZ",
            "tvgid": "KPSNLD2.us"
        },
        {
            "country": "United States",
            "name": "Weather Now",
            "tvgid": "WeatherNow.us"
        },
        {
            "country": "United States",
            "name": "Weather Now (K11LC-D5) Prescott, AZ",
            "tvgid": "K11LCD5.us"
        },
        {
            "country": "United States",
            "name": "Weather Now (WJXX2) Jacksonville, FL",
            "tvgid": "WJXX2.us"
        },
        {
            "country": "United States",
            "name": "Weather Plus (KPNX-DT2) Phoenix, AZ",
            "tvgid": "KPNX2.us"
        },
        {
            "country": "United States",
            "name": "WeatherNation",
            "tvgid": "WeatherNation.us"
        },
        {
            "country": "United States",
            "name": "WeatherNation (K18DR-DT9) Cortez, CO",
            "tvgid": "K18DRD9.us"
        },
        {
            "country": "United States",
            "name": "WeatherNation (KGPT-CD9) Wichita, KS",
            "tvgid": "KGPTCD9.us"
        },
        {
            "country": "United States",
            "name": "WeatherNation (KJTV-CD2) Lubbock, TX",
            "tvgid": "KJTVCD2.us"
        },
        {
            "country": "United States",
            "name": "WeatherNation (KMJC-LD6) Kansas City, KS",
            "tvgid": "KMJCLD6.us"
        },
        {
            "country": "United States",
            "name": "WeatherNation (KMJF-LD3) Columbus, NE",
            "tvgid": "KMJFLD3.us"
        },
        {
            "country": "United States",
            "name": "WeatherNation (KWBE-LD2) Beatrice, NE",
            "tvgid": "KWBELD2.us"
        },
        {
            "country": "United States",
            "name": "WeatherNation (KYTV-DT2) Springfield, MO",
            "tvgid": "KYTV2.us"
        },
        {
            "country": "United States",
            "name": "WeatherNation (WMTV6) Madison, WI",
            "tvgid": "WMTV6.us"
        },
        {
            "country": "United States",
            "name": "WeatherNation (WPEC-DT2) West Palm Beach, FL",
            "tvgid": "WPEC2.us"
        },
        {
            "country": "United States",
            "name": "WeatherNation (WPMI-TV2) Mobile, AL",
            "tvgid": "WPMITV2.us"
        },
        {
            "country": "United States",
            "name": "WeatherNation (WROB-DT6) Topeka, KS",
            "tvgid": "WROBLD6.us"
        },
        {
            "country": "United States",
            "name": "WeatherNation (WTVG7) Toledo, OH",
            "tvgid": "WTVG7.us"
        },
        {
            "country": "United States",
            "name": "WeatherNation (WVIR-TV2) Charlottesville, VA",
            "tvgid": "WVIRTV2.us"
        },
        {
            "country": "United States",
            "name": "WEFS - Cocoa, FL",
            "tvgid": "WEFS.us"
        },
        {
            "country": "United States",
            "name": "WEZK-LP - Knoxville, TN",
            "tvgid": "WEZKLP.us"
        },
        {
            "country": "United States",
            "name": "WFMZ-Allentown, PA",
            "tvgid": "WFMZTV.us"
        },
        {
            "country": "United States",
            "name": "WFPX-TV2 Fayetteville, NC",
            "tvgid": "WFPXTV2.us"
        },
        {
            "country": "United States",
            "name": "WFPX-TV3 Fayetteville, NC",
            "tvgid": "WFPXTV3.us"
        },
        {
            "country": "United States",
            "name": "WFPX-TV4 Fayetteville, NC",
            "tvgid": "WFPXTV4.us"
        },
        {
            "country": "United States",
            "name": "WFPX-TV5 Fayetteville, NC",
            "tvgid": "WFPXTV5.us"
        },
        {
            "country": "United States",
            "name": "WFPX-TV6 Raleigh, NC",
            "tvgid": "WFPXTV6.us"
        },
        {
            "country": "United States",
            "name": "WGGS Greenville, SC",
            "tvgid": "WGGSTV.us"
        },
        {
            "country": "United States",
            "name": "WGN-TV",
            "tvgid": "WGNTV.us"
        },
        {
            "country": "United States",
            "name": "WHDH Boston, MA",
            "tvgid": "WHDH.us"
        },
        {
            "country": "United States",
            "name": "WHKY Hickory, NC",
            "tvgid": "WHKYTV.us"
        },
        {
            "country": "United States",
            "name": "WHME South Bend, IN",
            "tvgid": "WHMETV.us"
        },
        {
            "country": "United States",
            "name": "Willow",
            "tvgid": "Willow.us"
        },
        {
            "country": "United States",
            "name": "Willow Cricket",
            "tvgid": "WillowCricket.us"
        },
        {
            "country": "United States",
            "name": "WILM-TV 10 Wilmington, NC",
            "tvgid": "WILMLD.us"
        },
        {
            "country": "United States",
            "name": "WILT-LD Wilmington, NC",
            "tvgid": "WILTLD.us"
        },
        {
            "country": "United States",
            "name": "WJAN-DT2 &quot;Teveo&quot; - Miami, FL",
            "tvgid": "WFUN.us"
        },
        {
            "country": "United States",
            "name": "WJCT More! Jacksonville, FL",
            "tvgid": "WJCT4.us"
        },
        {
            "country": "United States",
            "name": "WJTC-TV Mobile, AL",
            "tvgid": "WJTC.us"
        },
        {
            "country": "United States",
            "name": "WJYS &quot;The Way&quot; Chicago, IL",
            "tvgid": "WJYS.us"
        },
        {
            "country": "United States",
            "name": "WKBJ-LD2 Live Oak, FL",
            "tvgid": "WKBJLD2.us"
        },
        {
            "country": "United States",
            "name": "WKNX (ind) Knoxville, TN",
            "tvgid": "WKNXLP.us"
        },
        {
            "country": "United States",
            "name": "WLFB - Bluefield, WV",
            "tvgid": "WLFB.us"
        },
        {
            "country": "United States",
            "name": "WLFG - Grundy, VA",
            "tvgid": "WLFG.us"
        },
        {
            "country": "United States",
            "name": "WLFT Baton Rouge, LA",
            "tvgid": "WLFTCD.us"
        },
        {
            "country": "United States",
            "name": "WLLA Kalamazoo, MI",
            "tvgid": "WLLA.us"
        },
        {
            "country": "United States",
            "name": "WLMB Toledo, OH",
            "tvgid": "WLMB.us"
        },
        {
            "country": "United States",
            "name": "WLNY TV10/55, Riverhead, NY",
            "tvgid": "WLNYTV.us"
        },
        {
            "country": "United States",
            "name": "WLYH - Harrisburg, PA",
            "tvgid": "WLYHTV.us"
        },
        {
            "country": "United States",
            "name": "WMAH-FM (WMAH-TV4) Biloxi, MS",
            "tvgid": "WMAHTV4.us"
        },
        {
            "country": "United States",
            "name": "WMBC-Newton, NJ",
            "tvgid": "WMBCTV.us"
        },
        {
            "country": "United States",
            "name": "WMBQ-CD3 New York, NY",
            "tvgid": "WMBQCD3.us"
        },
        {
            "country": "United States",
            "name": "WMFP Boston, MA",
            "tvgid": "WMFP.us"
        },
        {
            "country": "United States",
            "name": "WMLW - Milwaukee, WI",
            "tvgid": "WMLWTV.us"
        },
        {
            "country": "United States",
            "name": "WMNN-LD MI-News Cadillac, MI",
            "tvgid": "WMNNLD.us"
        },
        {
            "country": "United States",
            "name": "WMOR-Tampa Bay, FL",
            "tvgid": "WMORTV.us"
        },
        {
            "country": "United States",
            "name": "WNHO-LP - Defiance, OH",
            "tvgid": "WNHOLP.us"
        },
        {
            "country": "United States",
            "name": "WNUE-FM Audio Only (WOTF-TV6) Daytona Beach, FL",
            "tvgid": "WOTFTV6.us"
        },
        {
            "country": "United States",
            "name": "WNYN-DT4 New York, NY",
            "tvgid": "WNYNLD4.us"
        },
        {
            "country": "United States",
            "name": "WNYN-DT5 New York, NY",
            "tvgid": "WNYNLD5.us"
        },
        {
            "country": "United States",
            "name": "World Fishing Network",
            "tvgid": "WorldFishingNetwork.us"
        },
        {
            "country": "United States",
            "name": "World Harvest (K14JS-DT2) Denver, CO",
            "tvgid": "K14JSD2.us"
        },
        {
            "country": "United States",
            "name": "World Harvest (WHNW-LD) Gary, IN",
            "tvgid": "WHNWLD.us"
        },
        {
            "country": "United States",
            "name": "World Harvest TV",
            "tvgid": "WorldHarvestTV.us"
        },
        {
            "country": "United States",
            "name": "Wow TV",
            "tvgid": "WowTV.us"
        },
        {
            "country": "United States",
            "name": "WPGA-TV Macon, GA",
            "tvgid": "WPGATV.us"
        },
        {
            "country": "United States",
            "name": "WPIX-TV",
            "tvgid": "WPIXTV.us"
        },
        {
            "country": "United States",
            "name": "WPXG-TV3 Concord, NH",
            "tvgid": "WPXGTV3.us"
        },
        {
            "country": "United States",
            "name": "WPXQ-TV3 Providence, RI",
            "tvgid": "WPXQTV3.us"
        },
        {
            "country": "United States",
            "name": "WRDQ - Orlando, FL",
            "tvgid": "WRDQ.us"
        },
        {
            "country": "United States",
            "name": "WSKY- Norfolk, VA",
            "tvgid": "WSKYTV.us"
        },
        {
            "country": "United States",
            "name": "WSOT Marion, IN",
            "tvgid": "WSOTLD.us"
        },
        {
            "country": "United States",
            "name": "WTGL - Orlando, FL",
            "tvgid": "WTGL.us"
        },
        {
            "country": "United States",
            "name": "WTJR Quincy, IL",
            "tvgid": "WTJR.us"
        },
        {
            "country": "United States",
            "name": "WTLW - Lima, OH",
            "tvgid": "WTLW.us"
        },
        {
            "country": "United States",
            "name": "WTSD-CA Philadelphia, PA",
            "tvgid": "WTSDCD.us"
        },
        {
            "country": "United States",
            "name": "WTTK-DT2 Kokomo, IN",
            "tvgid": "WTTK2.us"
        },
        {
            "country": "United States",
            "name": "WTTV-DT2 &quot;Indiana&apos;s 4.2&quot; Bloomington, IN",
            "tvgid": "WTTV2.us"
        },
        {
            "country": "United States",
            "name": "WTVE - Reading, PA",
            "tvgid": "WTVE.us"
        },
        {
            "country": "United States",
            "name": "WTVE-DT3 Reading, PA",
            "tvgid": "WTVE3.us"
        },
        {
            "country": "United States",
            "name": "WTVF-DT2 Nashville, TN",
            "tvgid": "WTVF2.us"
        },
        {
            "country": "United States",
            "name": "WTXI-DT2 Miami, FL",
            "tvgid": "WTXILD.us"
        },
        {
            "country": "United States",
            "name": "WTZT Athens, AL",
            "tvgid": "WTZTCD.us"
        },
        {
            "country": "United States",
            "name": "WVPX-TV3 Cleveland, OH",
            "tvgid": "WVPXTV3.us"
        },
        {
            "country": "United States",
            "name": "WWE Network",
            "tvgid": "WWENetwork.us"
        },
        {
            "country": "United States",
            "name": "WWE Network +1",
            "tvgid": "WWENetworkPlus1.us"
        },
        {
            "country": "United States",
            "name": "WWE Network Canada",
            "tvgid": "WWENetworkCanada.us"
        },
        {
            "country": "United States",
            "name": "WXIA-DT2 Weather Information Zone",
            "tvgid": "WXIATV2.us"
        },
        {
            "country": "United States",
            "name": "WXXA-TV4",
            "tvgid": "BounceTV4.us"
        },
        {
            "country": "United States",
            "name": "WYLN-LP Hazelton, PA",
            "tvgid": "WYLNLP.us"
        },
        {
            "country": "United States",
            "name": "WZZM-DT2 13 On Target Weather Grand Rapids, MI",
            "tvgid": "WZZM2.us"
        },
        {
            "country": "United States",
            "name": "XHDF-TDT",
            "tvgid": "XHDFTDT.us"
        },
        {
            "country": "United States",
            "name": "XTime Channel",
            "tvgid": "XTimeChannel.us"
        },
        {
            "country": "United States",
            "name": "Xtra",
            "tvgid": "Xtra.us"
        },
        {
            "country": "United States",
            "name": "Y2 (WDPB-DT2) Deaford, DE",
            "tvgid": "WDPB2.us"
        },
        {
            "country": "United States",
            "name": "Y2 (WHYY-DT2) Wilmington, DE",
            "tvgid": "WHYYTV2.us"
        },
        {
            "country": "United States",
            "name": "Yes Network",
            "tvgid": "YesNetwork.us"
        },
        {
            "country": "United States",
            "name": "YES Network",
            "tvgid": "YESNetwork.us"
        },
        {
            "country": "United States",
            "name": "YES2 Overflow",
            "tvgid": "YES2Overflow.us"
        },
        {
            "country": "United States",
            "name": "YouToo",
            "tvgid": "YouToo.us"
        },
        {
            "country": "United States",
            "name": "Youtoo America (KGCS) Joplin, MO",
            "tvgid": "KGCSLD.us"
        },
        {
            "country": "United States",
            "name": "Youtoo America (KHMP-LD2) Pahrump, NV",
            "tvgid": "KHMPLD2.us"
        },
        {
            "country": "United States",
            "name": "Youtoo America (KHMP-LD3) Pahrump, NV",
            "tvgid": "KHMPLD3.us"
        },
        {
            "country": "United States",
            "name": "Youtoo America (KKAX-LP) Kingman, AZ",
            "tvgid": "KKAXLP.us"
        },
        {
            "country": "United States",
            "name": "Youtoo America (KKEI-CD) Portland, OR",
            "tvgid": "KKEICD.us"
        },
        {
            "country": "United States",
            "name": "YouToo America (KMJD-LD8) Kalispell, MT",
            "tvgid": "KMJDLD8.us"
        },
        {
            "country": "United States",
            "name": "Youtoo America (KOMI-LP) Woodward, OK",
            "tvgid": "KOMICD.us"
        },
        {
            "country": "United States",
            "name": "Youtoo America (KORK-CD) Portland, OR",
            "tvgid": "KORKCD.us"
        },
        {
            "country": "United States",
            "name": "Youtoo America (KORS-DT2) Portland, OR",
            "tvgid": "KORSCD2.us"
        },
        {
            "country": "United States",
            "name": "YouToo America (KPVT-LD3) Las Vegas, NV",
            "tvgid": "KPVTLD3.us"
        },
        {
            "country": "United States",
            "name": "Youtoo America (KSLM-DT12) Portland, OR",
            "tvgid": "KSLMLD12.us"
        },
        {
            "country": "United States",
            "name": "Youtoo America (KSPK) Colorado Springs, CO",
            "tvgid": "KSPKLP.us"
        },
        {
            "country": "United States",
            "name": "Youtoo America (KWBJ-CD) Morgan City, LA",
            "tvgid": "KWBJCD.us"
        },
        {
            "country": "United States",
            "name": "Youtoo America (W18BB-D) Elizabeth City, NC",
            "tvgid": "W18BBD.us"
        },
        {
            "country": "United States",
            "name": "YouToo America (WBCF-LD2) Florence, AL",
            "tvgid": "WBCFLD2.us"
        },
        {
            "country": "United States",
            "name": "YouToo America (WBQP) Pensacola, FL",
            "tvgid": "WBQPCD.us"
        },
        {
            "country": "United States",
            "name": "Youtoo America (WCRD-LP) Carthage, IL",
            "tvgid": "WCRDLP.us"
        },
        {
            "country": "United States",
            "name": "YouToo America (WEQT-LD3) Atlanta, GA",
            "tvgid": "WEQTLD3.us"
        },
        {
            "country": "United States",
            "name": "Youtoo America (WFND-LD) Toledo, OH",
            "tvgid": "WFNDLD.us"
        },
        {
            "country": "United States",
            "name": "Youtoo America (WHHI) Hilton Head Island, SC",
            "tvgid": "W30CVD.us"
        },
        {
            "country": "United States",
            "name": "Youtoo America (WJNI-LD) North Charleston, SC",
            "tvgid": "WJNILD.us"
        },
        {
            "country": "United States",
            "name": "Youtoo America (WJTS) Jasper, IN",
            "tvgid": "WJTSCD.us"
        },
        {
            "country": "United States",
            "name": "Youtoo America (WLPD-CD) Plano, IL",
            "tvgid": "WLPDCD.us"
        },
        {
            "country": "United States",
            "name": "Youtoo America (WNCE-CD) Glens Falls, NY",
            "tvgid": "WNCECD.us"
        },
        {
            "country": "United States",
            "name": "Youtoo America (WOTH-CD5) Cincinnati, OH",
            "tvgid": "WOTHCD5.us"
        },
        {
            "country": "United States",
            "name": "Youtoo America (WREP-LD) Martinsville, IN",
            "tvgid": "WREPLD.us"
        },
        {
            "country": "United States",
            "name": "YouToo America (WSFD-LD) Perry, FL",
            "tvgid": "WSFDLD.us"
        },
        {
            "country": "United States",
            "name": "Youtoo America (WTBL) Lenoir, NC",
            "tvgid": "WTBLCD.us"
        },
        {
            "country": "United States",
            "name": "Youtoo America (WUWT) Union City, TN",
            "tvgid": "WUWTCD.us"
        },
        {
            "country": "United States",
            "name": "Youtoo America (WYKE) Citrus County, FL",
            "tvgid": "WYKECD.us"
        },
        {
            "country": "United States",
            "name": "Youtoo America (WZXZ-DT3) Orlando, FL",
            "tvgid": "WZXZCD3.us"
        },
        {
            "country": "United States",
            "name": "YTA TV",
            "tvgid": "YoutooAmerica.us"
        },
        {
            "country": "United States",
            "name": "YurView Arizona",
            "tvgid": "YurViewArizona.us"
        },
        {
            "country": "United States",
            "name": "YurView California",
            "tvgid": "YurViewCalifornia.us"
        },
        {
            "country": "United States",
            "name": "Z Living (WOCK-CD3) Chicago, IL",
            "tvgid": "WOCKCD3.us"
        },
        {
            "country": "United States",
            "name": "Z Living (WSKC-CD4) Atlanta, GA",
            "tvgid": "WSKCCD4.us"
        },
        {
            "country": "United States",
            "name": "Zion TV (KCIO-DT4) Ontario, CA",
            "tvgid": "KCIOLP4.us"
        },
        {
            "country": "United States",
            "name": "ZWTV (KFUL-DT9) San Luis Obipso, CA",
            "tvgid": "KFULLP9.us"
        },
        {
            "country": "United States",
            "name": "ZWTV (KJLA-DT9) Los Angeles, CA",
            "tvgid": "KJLA9.us"
        },
        {
            "country": "Uruguay",
            "name": "Canal 4",
            "tvgid": "Canal4.uy"
        },
        {
            "country": "Uruguay",
            "name": "TV Ciudad",
            "tvgid": "TVCiudad.uy"
        },
        {
            "country": "Uruguay",
            "name": "TV Nacional Uruguay",
            "tvgid": "TVNacionalUruguay.uy"
        },
        {
            "country": "Uruguay",
            "name": "Uruguay Natural TV",
            "tvgid": "UruguayNaturalTV.uy"
        },
        {
            "country": "Uruguay",
            "name": "VTV",
            "tvgid": "VTV.uy"
        },
        {
            "country": "Vanuatu",
            "name": "TV 2000",
            "tvgid": "TV2000.va"
        },
        {
            "country": "Venezuela",
            "name": "IVC",
            "tvgid": "IVC.ve"
        },
        {
            "country": "Venezuela",
            "name": "IVC Internacional",
            "tvgid": "IVCInternacional.ve"
        },
        {
            "country": "Venezuela",
            "name": "Sun Channel",
            "tvgid": "SunChannel.ve"
        },
        {
            "country": "Venezuela",
            "name": "Telesur",
            "tvgid": "Telesur.ve"
        },
        {
            "country": "Venezuela",
            "name": "Telesur English",
            "tvgid": "TelesurEnglish.ve"
        },
        {
            "country": "Venezuela",
            "name": "Televen",
            "tvgid": "Televen.ve"
        },
        {
            "country": "Venezuela",
            "name": "TV Familia",
            "tvgid": "TVFamilia.ve"
        },
        {
            "country": "Venezuela",
            "name": "Ve Plus Panregional",
            "tvgid": "VePlusPanregional.ve"
        },
        {
            "country": "Venezuela",
            "name": "Venevisión",
            "tvgid": "Venevision.ve"
        },
        {
            "country": "Venezuela",
            "name": "Venevisión Plus",
            "tvgid": "VenevisionPlus.ve"
        },
        {
            "country": "Viet Nam",
            "name": "VTV 1",
            "tvgid": "VTV1.vn"
        },
        {
            "country": "Viet Nam",
            "name": "VTV 2",
            "tvgid": "VTV2.vn"
        },
        {
            "country": "Viet Nam",
            "name": "VTV 3",
            "tvgid": "VTV3.vn"
        },
        {
            "country": "Viet Nam",
            "name": "VTV 4",
            "tvgid": "VTV4.vn"
        },
        {
            "country": "Mayotte",
            "name": "Kwezi TV",
            "tvgid": "KweziTV.yt"
        },
        {
            "country": "South Africa",
            "name": "1 Magic Africa",
            "tvgid": "1MagicAfrica.za"
        },
        {
            "country": "South Africa",
            "name": "1KZN TV",
            "tvgid": "1KZNTV.za"
        },
        {
            "country": "South Africa",
            "name": "Abol TV",
            "tvgid": "AbolTV.za"
        },
        {
            "country": "South Africa",
            "name": "Africa Magic Epic",
            "tvgid": "AfricaMagicEpic.za"
        },
        {
            "country": "South Africa",
            "name": "Africa Magic Family",
            "tvgid": "AfricaMagicFamily.za"
        },
        {
            "country": "South Africa",
            "name": "Africa Magic Hausa",
            "tvgid": "AfricaMagicHausa.za"
        },
        {
            "country": "South Africa",
            "name": "Africa Magic Igbo",
            "tvgid": "AfricaMagicIgbo.za"
        },
        {
            "country": "South Africa",
            "name": "Africa Magic Showcase Africa",
            "tvgid": "AfricaMagicShowcaseAfrica.za"
        },
        {
            "country": "South Africa",
            "name": "Africa Magic Urban",
            "tvgid": "AfricaMagicUrban.za"
        },
        {
            "country": "South Africa",
            "name": "Africa Magic Yoruba",
            "tvgid": "AfricaMagicYoruba.za"
        },
        {
            "country": "South Africa",
            "name": "Boom TV",
            "tvgid": "BoomTV.za"
        },
        {
            "country": "South Africa",
            "name": "BusinessDay TV",
            "tvgid": "BusinessDayTV.za"
        },
        {
            "country": "South Africa",
            "name": "Cape Town TV",
            "tvgid": "CapeTownTV.za"
        },
        {
            "country": "South Africa",
            "name": "Channel O",
            "tvgid": "ChannelO.za"
        },
        {
            "country": "South Africa",
            "name": "Dumisa TV",
            "tvgid": "DumisaTV.za"
        },
        {
            "country": "South Africa",
            "name": "E Extra",
            "tvgid": "EExtra.za"
        },
        {
            "country": "South Africa",
            "name": "E Movies",
            "tvgid": "EMovies.za"
        },
        {
            "country": "South Africa",
            "name": "E Movies Extra",
            "tvgid": "EMoviesExtra.za"
        },
        {
            "country": "South Africa",
            "name": "E Toonz",
            "tvgid": "EToonz.za"
        },
        {
            "country": "South Africa",
            "name": "E TV",
            "tvgid": "ETV.za"
        },
        {
            "country": "South Africa",
            "name": "E TV Africa",
            "tvgid": "ETVAfrica.za"
        },
        {
            "country": "South Africa",
            "name": "ENews Channel Africa",
            "tvgid": "ENewsChannelAfrica.za"
        },
        {
            "country": "South Africa",
            "name": "Faith Africa",
            "tvgid": "FaithAfrica.za"
        },
        {
            "country": "South Africa",
            "name": "FliekNet",
            "tvgid": "FliekNet.za"
        },
        {
            "country": "South Africa",
            "name": "Gau TV",
            "tvgid": "GauTV.za"
        },
        {
            "country": "South Africa",
            "name": "Honey",
            "tvgid": "Honey.za"
        },
        {
            "country": "South Africa",
            "name": "Ignition",
            "tvgid": "Ignition.za"
        },
        {
            "country": "South Africa",
            "name": "ITV Networks",
            "tvgid": "ITVNetworks.za"
        },
        {
            "country": "South Africa",
            "name": "KykNet",
            "tvgid": "KykNet.za"
        },
        {
            "country": "South Africa",
            "name": "KykNet &amp;amp; Kie",
            "tvgid": "KykNetKie.za"
        },
        {
            "country": "South Africa",
            "name": "KykNet Nou!",
            "tvgid": "KykNetNou.za"
        },
        {
            "country": "South Africa",
            "name": "M-Net East",
            "tvgid": "MNetEast.za"
        },
        {
            "country": "South Africa",
            "name": "M-Net Movies 1 East Africa",
            "tvgid": "MNetMovies1EastAfrica.za"
        },
        {
            "country": "South Africa",
            "name": "M-Net Movies 1 West Africa",
            "tvgid": "MNetMovies1WestAfrica.za"
        },
        {
            "country": "South Africa",
            "name": "M-Net Movies 2",
            "tvgid": "MNetMovies2.za"
        },
        {
            "country": "South Africa",
            "name": "M-Net Movies 3",
            "tvgid": "MNetMovies3.za"
        },
        {
            "country": "South Africa",
            "name": "M-Net Movies 4",
            "tvgid": "MNetMovies4.za"
        },
        {
            "country": "South Africa",
            "name": "M-Net South Africa",
            "tvgid": "MNetSouthAfrica.za"
        },
        {
            "country": "South Africa",
            "name": "M-Net West",
            "tvgid": "MNetWest.za"
        },
        {
            "country": "South Africa",
            "name": "Maisha Magic Bongo",
            "tvgid": "MaishaMagicBongo.za"
        },
        {
            "country": "South Africa",
            "name": "Maisha Magic Movies",
            "tvgid": "MaishaMagicMovies.za"
        },
        {
            "country": "South Africa",
            "name": "Maisha Magic Plus",
            "tvgid": "MaishaMagicPlus.za"
        },
        {
            "country": "South Africa",
            "name": "Maisha Magic Poa",
            "tvgid": "MaishaMagicPoa.za"
        },
        {
            "country": "South Africa",
            "name": "Mindset Learn",
            "tvgid": "MindsetLearn.za"
        },
        {
            "country": "South Africa",
            "name": "Moja Love",
            "tvgid": "MojaLove.za"
        },
        {
            "country": "South Africa",
            "name": "Mpuma Kapa TV",
            "tvgid": "MpumaKapaTV.za"
        },
        {
            "country": "South Africa",
            "name": "Mzansi Bioskop",
            "tvgid": "MzansiBioskop.za"
        },
        {
            "country": "South Africa",
            "name": "Mzansi Magic",
            "tvgid": "MzansiMagic.za"
        },
        {
            "country": "South Africa",
            "name": "Mzansi Magic Music",
            "tvgid": "MzansiMagicMusic.za"
        },
        {
            "country": "South Africa",
            "name": "Mzansi Wethu",
            "tvgid": "MzansiWethu.za"
        },
        {
            "country": "South Africa",
            "name": "Newzroom Afrika",
            "tvgid": "NewzroomAfrika.za"
        },
        {
            "country": "South Africa",
            "name": "Novela Magic",
            "tvgid": "NovelaMagic.za"
        },
        {
            "country": "South Africa",
            "name": "One Gospel",
            "tvgid": "OneGospel.za"
        },
        {
            "country": "South Africa",
            "name": "OneZed",
            "tvgid": "OneZed.za"
        },
        {
            "country": "South Africa",
            "name": "Parliament TV",
            "tvgid": "ParliamentTV.za"
        },
        {
            "country": "South Africa",
            "name": "Pearl Magic Prime",
            "tvgid": "PearlMagicPrime.za"
        },
        {
            "country": "South Africa",
            "name": "People&amp;apos;s Weather",
            "tvgid": "PeoplesWeather.za"
        },
        {
            "country": "South Africa",
            "name": "SABC 1",
            "tvgid": "SABC1.za"
        },
        {
            "country": "South Africa",
            "name": "SABC 2",
            "tvgid": "SABC2.za"
        },
        {
            "country": "South Africa",
            "name": "SABC 3",
            "tvgid": "SABC3.za"
        },
        {
            "country": "South Africa",
            "name": "SABC News",
            "tvgid": "SABCNews.za"
        },
        {
            "country": "South Africa",
            "name": "Soweto TV",
            "tvgid": "SowetoTV.za"
        },
        {
            "country": "South Africa",
            "name": "SuperSport Action Africa",
            "tvgid": "SuperSportActionAfrica.za"
        },
        {
            "country": "South Africa",
            "name": "SuperSport Blitz Africa",
            "tvgid": "SuperSportBlitzAfrica.za"
        },
        {
            "country": "South Africa",
            "name": "SuperSport Cricket Africa",
            "tvgid": "SuperSportCricketAfrica.za"
        },
        {
            "country": "South Africa",
            "name": "SuperSport Football Africa",
            "tvgid": "SuperSportFootballAfrica.za"
        },
        {
            "country": "South Africa",
            "name": "SuperSport Football Plus Africa",
            "tvgid": "SuperSportFootballPlusAfrica.za"
        },
        {
            "country": "South Africa",
            "name": "SuperSport Golf Africa",
            "tvgid": "SuperSportGolfAfrica.za"
        },
        {
            "country": "South Africa",
            "name": "SuperSport Grandstand Africa",
            "tvgid": "SuperSportGrandstandAfrica.za"
        },
        {
            "country": "South Africa",
            "name": "SuperSport LaLiga Africa",
            "tvgid": "SuperSportLaLigaAfrica.za"
        },
        {
            "country": "South Africa",
            "name": "SuperSport Motorsport Africa",
            "tvgid": "SuperSportMotorsportAfrica.za"
        },
        {
            "country": "South Africa",
            "name": "SuperSport Máximo 1 Africa",
            "tvgid": "SuperSportMaximo1Africa.za"
        },
        {
            "country": "South Africa",
            "name": "SuperSport Máximo 2 Africa",
            "tvgid": "SuperSportMaximo2Africa.za"
        },
        {
            "country": "South Africa",
            "name": "SuperSport Máximo 360",
            "tvgid": "SuperSportMaximo360.za"
        },
        {
            "country": "South Africa",
            "name": "SuperSport Play",
            "tvgid": "SuperSportPlay.za"
        },
        {
            "country": "South Africa",
            "name": "SuperSport Premier League Africa",
            "tvgid": "SuperSportPremierLeagueAfrica.za"
        },
        {
            "country": "South Africa",
            "name": "SuperSport PSL",
            "tvgid": "SuperSportPSL.za"
        },
        {
            "country": "South Africa",
            "name": "SuperSport Rugby Africa",
            "tvgid": "SuperSportRugbyAfrica.za"
        },
        {
            "country": "South Africa",
            "name": "SuperSport Tennis Africa",
            "tvgid": "SuperSportTennisAfrica.za"
        },
        {
            "country": "South Africa",
            "name": "SuperSport Variety 1 Africa",
            "tvgid": "SuperSportVariety1Africa.za"
        },
        {
            "country": "South Africa",
            "name": "SuperSport Variety 2 Africa",
            "tvgid": "SuperSportVariety2Africa.za"
        },
        {
            "country": "South Africa",
            "name": "SuperSport Variety 3 Africa",
            "tvgid": "SuperSportVariety3Africa.za"
        },
        {
            "country": "South Africa",
            "name": "SuperSport Variety 4 Africa",
            "tvgid": "SuperSportVariety4Africa.za"
        },
        {
            "country": "South Africa",
            "name": "Tellytrack 1",
            "tvgid": "Tellytrack1.za"
        },
        {
            "country": "South Africa",
            "name": "The Home Channel",
            "tvgid": "TheHomeChannel.za"
        },
        {
            "country": "South Africa",
            "name": "Tshwane TV",
            "tvgid": "TshwaneTV.za"
        },
        {
            "country": "South Africa",
            "name": "Urban TV",
            "tvgid": "UrbanTV.za"
        },
        {
            "country": "South Africa",
            "name": "Via",
            "tvgid": "Via.za"
        },
        {
            "country": "South Africa",
            "name": "WildEarth",
            "tvgid": "WildEarth.za"
        },
        {
            "country": "South Africa",
            "name": "WWE Channel",
            "tvgid": "WWEChannel.za"
        },
        {
            "country": "South Africa",
            "name": "Zambezi Magic",
            "tvgid": "ZambeziMagic.za"
        },
        {
            "country": "Zambia",
            "name": "Camnet TV",
            "tvgid": "CamnetTV.zm"
        },
        {
            "country": "Zambia",
            "name": "Diamond TV",
            "tvgid": "DiamondTV.zm"
        },
        {
            "country": "Zambia",
            "name": "KBN",
            "tvgid": "KBN.zm"
        },
        {
            "country": "Zambia",
            "name": "Parliament TV",
            "tvgid": "ParliamentTV.zm"
        },
        {
            "country": "Zambia",
            "name": "Power TV",
            "tvgid": "PowerTV.zm"
        },
        {
            "country": "Zambia",
            "name": "ZNBC TV 1",
            "tvgid": "ZNBCTV1.zm"
        },
        {
            "country": "Zambia",
            "name": "ZNBC TV 2",
            "tvgid": "ZNBCTV2.zm"
        },
        {
            "country": "Zimbabwe",
            "name": "Yadah TV",
            "tvgid": "YadahTV.zw"
        },
        {
            "country": "Zimbabwe",
            "name": "ZBC TV",
            "tvgid": "ZBCTV.zw"
        }
]